rvo23d.cp311-win_amd64.pyd
jt_pyrvo23d-0.1.6.dist-info/licenses/AUTHORS
jt_pyrvo23d-0.1.6.dist-info/licenses/LICENSE
jt_pyrvo23d-0.1.6.dist-info/METADATA
jt_pyrvo23d-0.1.6.dist-info/WHEEL
jt_pyrvo23d-0.1.6.dist-info/top_level.txt
jt_pyrvo23d-0.1.6.dist-info/RECORD
